{
  "subject": "MTH",
  "totalPages": 168,
  "matchedPages": 159,
  "pages": {
    "1": null,
    "2": {
      "topic": "mth-6-1",
      "chapter": "mth-ch6-ratio",
      "score": 0.529
    },
    "3": {
      "topic": "mth-3-1",
      "chapter": "mth-ch3-algebra",
      "score": 1.286
    },
    "4": {
      "topic": "mth-1-4",
      "chapter": "mth-ch1-sets",
      "score": 1.19
    },
    "5": {
      "topic": "mth-3-3",
      "chapter": "mth-ch3-algebra",
      "score": 1.231
    },
    "6": {
      "topic": "mth-6-1",
      "chapter": "mth-ch6-ratio",
      "score": 1.471
    },
    "7": {
      "topic": "mth-1-1",
      "chapter": "mth-ch1-sets",
      "score": 3.375
    },
    "8": {
      "topic": "mth-1-1",
      "chapter": "mth-ch1-sets",
      "score": 4.167
    },
    "9": {
      "topic": "mth-1-3",
      "chapter": "mth-ch1-sets",
      "score": 2.909
    },
    "10": {
      "topic": "mth-1-1",
      "chapter": "mth-ch1-sets",
      "score": 0.375
    },
    "11": {
      "topic": "mth-1-1",
      "chapter": "mth-ch1-sets",
      "score": 1.5
    },
    "12": {
      "topic": "mth-1-4",
      "chapter": "mth-ch1-sets",
      "score": 0.762
    },
    "13": {
      "topic": "mth-1-3",
      "chapter": "mth-ch1-sets",
      "score": 1.136
    },
    "14": {
      "topic": "mth-1-3",
      "chapter": "mth-ch1-sets",
      "score": 1.136
    },
    "15": {
      "topic": "mth-6-1",
      "chapter": "mth-ch6-ratio",
      "score": 0.941
    },
    "16": {
      "topic": "mth-1-2",
      "chapter": "mth-ch1-sets",
      "score": 1.316
    },
    "17": {
      "topic": "mth-1-4",
      "chapter": "mth-ch1-sets",
      "score": 3.048
    },
    "18": {
      "topic": "mth-1-4",
      "chapter": "mth-ch1-sets",
      "score": 0.762
    },
    "19": {
      "topic": "mth-1-5",
      "chapter": "mth-ch1-sets",
      "score": 1.8
    },
    "20": {
      "topic": "mth-6-1",
      "chapter": "mth-ch6-ratio",
      "score": 0.529
    },
    "21": {
      "topic": "mth-6-1",
      "chapter": "mth-ch6-ratio",
      "score": 0.941
    },
    "22": {
      "topic": "mth-1-2",
      "chapter": "mth-ch1-sets",
      "score": 0.474
    },
    "23": {
      "topic": "mth-6-1",
      "chapter": "mth-ch6-ratio",
      "score": 0.529
    },
    "24": {
      "topic": "mth-1-1",
      "chapter": "mth-ch1-sets",
      "score": 0.167
    },
    "25": {
      "topic": "mth-6-1",
      "chapter": "mth-ch6-ratio",
      "score": 0.529
    },
    "26": {
      "topic": "mth-2-1",
      "chapter": "mth-ch2-reals",
      "score": 1.895
    },
    "27": {
      "topic": "mth-3-3",
      "chapter": "mth-ch3-algebra",
      "score": 1.923
    },
    "28": {
      "topic": "mth-6-1",
      "chapter": "mth-ch6-ratio",
      "score": 0.941
    },
    "29": {
      "topic": "mth-3-1",
      "chapter": "mth-ch3-algebra",
      "score": 0.893
    },
    "30": {
      "topic": "mth-3-3",
      "chapter": "mth-ch3-algebra",
      "score": 1.231
    },
    "31": {
      "topic": "mth-7-1",
      "chapter": "mth-ch7-stats",
      "score": 0.889
    },
    "32": {
      "topic": "mth-3-1",
      "chapter": "mth-ch3-algebra",
      "score": 0.571
    },
    "33": {
      "topic": "mth-6-1",
      "chapter": "mth-ch6-ratio",
      "score": 0.941
    },
    "34": {
      "topic": "mth-1-4",
      "chapter": "mth-ch1-sets",
      "score": 1.19
    },
    "35": {
      "topic": "mth-6-1",
      "chapter": "mth-ch6-ratio",
      "score": 0.529
    },
    "36": {
      "topic": "mth-3-3",
      "chapter": "mth-ch3-algebra",
      "score": 0.692
    },
    "37": {
      "topic": "mth-3-3",
      "chapter": "mth-ch3-algebra",
      "score": 0.692
    },
    "38": {
      "topic": "mth-3-3",
      "chapter": "mth-ch3-algebra",
      "score": 0.692
    },
    "39": {
      "topic": "mth-6-1",
      "chapter": "mth-ch6-ratio",
      "score": 1.471
    },
    "40": {
      "topic": "mth-2-2",
      "chapter": "mth-ch2-reals",
      "score": 2.118
    },
    "41": {
      "topic": "mth-2-2",
      "chapter": "mth-ch2-reals",
      "score": 0.941
    },
    "42": {
      "topic": "mth-2-2",
      "chapter": "mth-ch2-reals",
      "score": 1.471
    },
    "43": {
      "topic": "mth-3-3",
      "chapter": "mth-ch3-algebra",
      "score": 1.923
    },
    "44": {
      "topic": "mth-6-1",
      "chapter": "mth-ch6-ratio",
      "score": 1.471
    },
    "45": {
      "topic": "mth-6-1",
      "chapter": "mth-ch6-ratio",
      "score": 1.471
    },
    "46": {
      "topic": "mth-3-3",
      "chapter": "mth-ch3-algebra",
      "score": 1.231
    },
    "47": {
      "topic": "mth-2-1",
      "chapter": "mth-ch2-reals",
      "score": 1.895
    },
    "48": {
      "topic": "mth-6-1",
      "chapter": "mth-ch6-ratio",
      "score": 0.941
    },
    "49": {
      "topic": "mth-1-4",
      "chapter": "mth-ch1-sets",
      "score": 0.762
    },
    "50": {
      "topic": "mth-1-4",
      "chapter": "mth-ch1-sets",
      "score": 0.762
    },
    "51": {
      "topic": "mth-1-3",
      "chapter": "mth-ch1-sets",
      "score": 0.409
    },
    "52": {
      "topic": "mth-6-1",
      "chapter": "mth-ch6-ratio",
      "score": 0.529
    },
    "53": {
      "topic": "mth-4-2",
      "chapter": "mth-ch4-equations",
      "score": 0.941
    },
    "54": {
      "topic": "mth-6-1",
      "chapter": "mth-ch6-ratio",
      "score": 0.941
    },
    "55": {
      "topic": "mth-8-1",
      "chapter": "mth-ch8-prob",
      "score": 0.308
    },
    "56": {
      "topic": "mth-4-1",
      "chapter": "mth-ch4-equations",
      "score": 0.391
    },
    "57": {
      "topic": "mth-8-1",
      "chapter": "mth-ch8-prob",
      "score": 0.308
    },
    "58": {
      "topic": "mth-3-1",
      "chapter": "mth-ch3-algebra",
      "score": 0.321
    },
    "59": {
      "topic": "mth-3-3",
      "chapter": "mth-ch3-algebra",
      "score": 0.308
    },
    "60": null,
    "61": {
      "topic": "mth-3-3",
      "chapter": "mth-ch3-algebra",
      "score": 0.692
    },
    "62": {
      "topic": "mth-3-1",
      "chapter": "mth-ch3-algebra",
      "score": 3.571
    },
    "63": {
      "topic": "mth-3-1",
      "chapter": "mth-ch3-algebra",
      "score": 1.286
    },
    "64": {
      "topic": "mth-3-1",
      "chapter": "mth-ch3-algebra",
      "score": 1.75
    },
    "65": {
      "topic": "mth-3-1",
      "chapter": "mth-ch3-algebra",
      "score": 0.571
    },
    "66": {
      "topic": "mth-4-1",
      "chapter": "mth-ch4-equations",
      "score": 0.174
    },
    "67": {
      "topic": "mth-3-3",
      "chapter": "mth-ch3-algebra",
      "score": 0.692
    },
    "68": {
      "topic": "mth-1-4",
      "chapter": "mth-ch1-sets",
      "score": 1.19
    },
    "69": {
      "topic": "mth-3-2",
      "chapter": "mth-ch3-algebra",
      "score": 0.571
    },
    "70": {
      "topic": "mth-6-1",
      "chapter": "mth-ch6-ratio",
      "score": 0.941
    },
    "71": {
      "topic": "mth-4-2",
      "chapter": "mth-ch4-equations",
      "score": 0.235
    },
    "72": {
      "topic": "mth-6-1",
      "chapter": "mth-ch6-ratio",
      "score": 0.941
    },
    "73": null,
    "74": {
      "topic": "mth-4-1",
      "chapter": "mth-ch4-equations",
      "score": 0.391
    },
    "75": {
      "topic": "mth-6-1",
      "chapter": "mth-ch6-ratio",
      "score": 0.235
    },
    "76": {
      "topic": "mth-6-1",
      "chapter": "mth-ch6-ratio",
      "score": 0.941
    },
    "77": {
      "topic": "mth-3-2",
      "chapter": "mth-ch3-algebra",
      "score": 0.571
    },
    "78": {
      "topic": "mth-6-1",
      "chapter": "mth-ch6-ratio",
      "score": 0.941
    },
    "79": {
      "topic": "mth-4-1",
      "chapter": "mth-ch4-equations",
      "score": 0.696
    },
    "80": {
      "topic": "mth-6-1",
      "chapter": "mth-ch6-ratio",
      "score": 0.941
    },
    "81": {
      "topic": "mth-3-1",
      "chapter": "mth-ch3-algebra",
      "score": 2.286
    },
    "82": {
      "topic": "mth-3-1",
      "chapter": "mth-ch3-algebra",
      "score": 0.571
    },
    "83": {
      "topic": "mth-1-1",
      "chapter": "mth-ch1-sets",
      "score": 0.375
    },
    "84": {
      "topic": "mth-4-2",
      "chapter": "mth-ch4-equations",
      "score": 0.235
    },
    "85": {
      "topic": "mth-1-3",
      "chapter": "mth-ch1-sets",
      "score": 0.727
    },
    "86": null,
    "87": {
      "topic": "mth-3-1",
      "chapter": "mth-ch3-algebra",
      "score": 0.893
    },
    "88": {
      "topic": "mth-8-1",
      "chapter": "mth-ch8-prob",
      "score": 0.308
    },
    "89": {
      "topic": "mth-4-2",
      "chapter": "mth-ch4-equations",
      "score": 0.529
    },
    "90": {
      "topic": "mth-3-3",
      "chapter": "mth-ch3-algebra",
      "score": 1.231
    },
    "91": {
      "topic": "mth-3-3",
      "chapter": "mth-ch3-algebra",
      "score": 0.692
    },
    "92": null,
    "93": {
      "topic": "mth-3-3",
      "chapter": "mth-ch3-algebra",
      "score": 0.692
    },
    "94": null,
    "95": {
      "topic": "mth-4-1",
      "chapter": "mth-ch4-equations",
      "score": 4.348
    },
    "96": {
      "topic": "mth-6-1",
      "chapter": "mth-ch6-ratio",
      "score": 0.941
    },
    "97": {
      "topic": "mth-6-1",
      "chapter": "mth-ch6-ratio",
      "score": 0.941
    },
    "98": {
      "topic": "mth-3-3",
      "chapter": "mth-ch3-algebra",
      "score": 1.231
    },
    "99": {
      "topic": "mth-4-1",
      "chapter": "mth-ch4-equations",
      "score": 2.13
    },
    "100": {
      "topic": "mth-4-2",
      "chapter": "mth-ch4-equations",
      "score": 0.235
    },
    "101": {
      "topic": "mth-1-3",
      "chapter": "mth-ch1-sets",
      "score": 0.727
    },
    "102": {
      "topic": "mth-6-1",
      "chapter": "mth-ch6-ratio",
      "score": 0.941
    },
    "103": {
      "topic": "mth-6-1",
      "chapter": "mth-ch6-ratio",
      "score": 0.941
    },
    "104": {
      "topic": "mth-1-3",
      "chapter": "mth-ch1-sets",
      "score": 1.136
    },
    "105": {
      "topic": "mth-6-1",
      "chapter": "mth-ch6-ratio",
      "score": 0.235
    },
    "106": {
      "topic": "mth-1-5",
      "chapter": "mth-ch1-sets",
      "score": 1.25
    },
    "107": {
      "topic": "mth-5-1",
      "chapter": "mth-ch5-coord",
      "score": 3.267
    },
    "108": {
      "topic": "mth-5-1",
      "chapter": "mth-ch5-coord",
      "score": 1.067
    },
    "109": {
      "topic": "mth-5-1",
      "chapter": "mth-ch5-coord",
      "score": 0.6
    },
    "110": {
      "topic": "mth-1-3",
      "chapter": "mth-ch1-sets",
      "score": 1.136
    },
    "111": {
      "topic": "mth-3-1",
      "chapter": "mth-ch3-algebra",
      "score": 1.286
    },
    "112": {
      "topic": "mth-6-1",
      "chapter": "mth-ch6-ratio",
      "score": 0.941
    },
    "113": {
      "topic": "mth-6-1",
      "chapter": "mth-ch6-ratio",
      "score": 0.941
    },
    "114": {
      "topic": "mth-6-1",
      "chapter": "mth-ch6-ratio",
      "score": 0.529
    },
    "115": {
      "topic": "mth-4-1",
      "chapter": "mth-ch4-equations",
      "score": 1.087
    },
    "116": {
      "topic": "mth-4-1",
      "chapter": "mth-ch4-equations",
      "score": 0.696
    },
    "117": {
      "topic": "mth-6-1",
      "chapter": "mth-ch6-ratio",
      "score": 0.941
    },
    "118": {
      "topic": "mth-6-1",
      "chapter": "mth-ch6-ratio",
      "score": 2.882
    },
    "119": {
      "topic": "mth-6-1",
      "chapter": "mth-ch6-ratio",
      "score": 2.118
    },
    "120": {
      "topic": "mth-6-1",
      "chapter": "mth-ch6-ratio",
      "score": 2.118
    },
    "121": {
      "topic": "mth-6-1",
      "chapter": "mth-ch6-ratio",
      "score": 1.471
    },
    "122": {
      "topic": "mth-1-2",
      "chapter": "mth-ch1-sets",
      "score": 0.211
    },
    "123": null,
    "124": null,
    "125": {
      "topic": "mth-1-4",
      "chapter": "mth-ch1-sets",
      "score": 0.429
    },
    "126": {
      "topic": "mth-6-1",
      "chapter": "mth-ch6-ratio",
      "score": 0.941
    },
    "127": {
      "topic": "mth-6-1",
      "chapter": "mth-ch6-ratio",
      "score": 0.529
    },
    "128": {
      "topic": "mth-6-1",
      "chapter": "mth-ch6-ratio",
      "score": 0.235
    },
    "129": {
      "topic": "mth-8-1",
      "chapter": "mth-ch8-prob",
      "score": 0.308
    },
    "130": {
      "topic": "mth-6-1",
      "chapter": "mth-ch6-ratio",
      "score": 0.941
    },
    "131": {
      "topic": "mth-6-1",
      "chapter": "mth-ch6-ratio",
      "score": 1.471
    },
    "132": {
      "topic": "mth-7-1",
      "chapter": "mth-ch7-stats",
      "score": 1.389
    },
    "133": {
      "topic": "mth-7-1",
      "chapter": "mth-ch7-stats",
      "score": 3.556
    },
    "134": {
      "topic": "mth-7-1",
      "chapter": "mth-ch7-stats",
      "score": 1.389
    },
    "135": {
      "topic": "mth-6-1",
      "chapter": "mth-ch6-ratio",
      "score": 0.941
    },
    "136": {
      "topic": "mth-7-1",
      "chapter": "mth-ch7-stats",
      "score": 0.889
    },
    "137": {
      "topic": "mth-6-1",
      "chapter": "mth-ch6-ratio",
      "score": 0.529
    },
    "138": {
      "topic": "mth-3-1",
      "chapter": "mth-ch3-algebra",
      "score": 0.321
    },
    "139": {
      "topic": "mth-6-1",
      "chapter": "mth-ch6-ratio",
      "score": 1.471
    },
    "140": {
      "topic": "mth-6-1",
      "chapter": "mth-ch6-ratio",
      "score": 1.471
    },
    "141": {
      "topic": "mth-7-1",
      "chapter": "mth-ch7-stats",
      "score": 0.889
    },
    "142": {
      "topic": "mth-8-1",
      "chapter": "mth-ch8-prob",
      "score": 0.692
    },
    "143": {
      "topic": "mth-1-3",
      "chapter": "mth-ch1-sets",
      "score": 0.409
    },
    "144": {
      "topic": "mth-6-1",
      "chapter": "mth-ch6-ratio",
      "score": 0.941
    },
    "145": {
      "topic": "mth-6-1",
      "chapter": "mth-ch6-ratio",
      "score": 0.529
    },
    "146": {
      "topic": "mth-6-1",
      "chapter": "mth-ch6-ratio",
      "score": 0.529
    },
    "147": {
      "topic": "mth-7-1",
      "chapter": "mth-ch7-stats",
      "score": 0.222
    },
    "148": {
      "topic": "mth-6-1",
      "chapter": "mth-ch6-ratio",
      "score": 0.235
    },
    "149": {
      "topic": "mth-1-3",
      "chapter": "mth-ch1-sets",
      "score": 0.409
    },
    "150": {
      "topic": "mth-1-4",
      "chapter": "mth-ch1-sets",
      "score": 0.762
    },
    "151": {
      "topic": "mth-6-1",
      "chapter": "mth-ch6-ratio",
      "score": 0.941
    },
    "152": {
      "topic": "mth-1-3",
      "chapter": "mth-ch1-sets",
      "score": 0.409
    },
    "153": {
      "topic": "mth-1-1",
      "chapter": "mth-ch1-sets",
      "score": 0.167
    },
    "154": {
      "topic": "mth-8-1",
      "chapter": "mth-ch8-prob",
      "score": 1.231
    },
    "155": {
      "topic": "mth-8-1",
      "chapter": "mth-ch8-prob",
      "score": 1.923
    },
    "156": {
      "topic": "mth-6-1",
      "chapter": "mth-ch6-ratio",
      "score": 0.941
    },
    "157": {
      "topic": "mth-6-1",
      "chapter": "mth-ch6-ratio",
      "score": 0.941
    },
    "158": {
      "topic": "mth-8-1",
      "chapter": "mth-ch8-prob",
      "score": 0.692
    },
    "159": {
      "topic": "mth-8-1",
      "chapter": "mth-ch8-prob",
      "score": 0.692
    },
    "160": {
      "topic": "mth-8-1",
      "chapter": "mth-ch8-prob",
      "score": 0.692
    },
    "161": {
      "topic": "mth-1-1",
      "chapter": "mth-ch1-sets",
      "score": 1.042
    },
    "162": {
      "topic": "mth-1-3",
      "chapter": "mth-ch1-sets",
      "score": 0.409
    },
    "163": {
      "topic": "mth-6-1",
      "chapter": "mth-ch6-ratio",
      "score": 0.235
    },
    "164": {
      "topic": "mth-6-1",
      "chapter": "mth-ch6-ratio",
      "score": 0.529
    },
    "165": null,
    "166": {
      "topic": "mth-8-1",
      "chapter": "mth-ch8-prob",
      "score": 0.308
    },
    "167": {
      "topic": "mth-4-1",
      "chapter": "mth-ch4-equations",
      "score": 0.391
    },
    "168": {
      "topic": "mth-6-1",
      "chapter": "mth-ch6-ratio",
      "score": 0.235
    }
  }
}